neuralnet_visualize/__init__.py
neuralnet_visualize/exceptions.py
neuralnet_visualize/visualize.py
neuralnet_visualize-0.2.3.dist-info/LICENSE
neuralnet_visualize-0.2.3.dist-info/METADATA
neuralnet_visualize-0.2.3.dist-info/WHEEL
neuralnet_visualize-0.2.3.dist-info/top_level.txt
neuralnet_visualize-0.2.3.dist-info/RECORD
