Metadata-Version: 2.1
Name: neuralnet-visualize
Version: 0.2.3
Summary: Generate a neural network architecture Image
Home-page: https://github.com/AnuragAnalog/nn_visualize
Author: Anurag Peddi
Author-email: anurag.peddi1998@gmail.com
License: Apache License 2.0
Download-URL: https://pypi.org/project/neuralnet-visualize/
Keywords: Deep,Visualizer,Neural,Network,Visualize,Graphviz,Python
Platform: UNKNOWN
Classifier: Natural Language :: English
Classifier: Intended Audience :: Developers
Classifier: Intended Audience :: Science/Research
Classifier: Programming Language :: Python :: 2
Classifier: Programming Language :: Python :: 2.7
Classifier: Programming Language :: Python :: 3
Classifier: Programming Language :: Python :: 3.5
Classifier: Programming Language :: Python :: 3.6
Classifier: Programming Language :: Python :: Implementation
Classifier: Operating System :: OS Independent
Classifier: License :: OSI Approved :: Apache Software License
Classifier: Topic :: Software Development :: Libraries :: Python Modules
Classifier: Topic :: Scientific/Engineering :: Visualization
Classifier: Topic :: Scientific/Engineering :: Artificial Intelligence
Requires-Python: >=2.7
Requires-Dist: graphviz (>=0.14)
